mamaduck/__init__.py
mamaduck/connectors/csv.py
mamaduck/connectors/psql.py
mamaduck/connectors/sqlite.py
mamaduck/database/__init__.py
mamaduck/database/duckdb.py
mamaduck/kwak.py
mamaduck/sink/to_csv.py
mamaduck/sink/to_psql.py
mamaduck/sink/to_sqlite.py
mamaduck-1.0.2.dist-info/METADATA
mamaduck-1.0.2.dist-info/WHEEL
mamaduck-1.0.2.dist-info/entry_points.txt
mamaduck-1.0.2.dist-info/RECORD
