Metadata-Version: 2.1
Name: mamaduck
Version: 1.0.2
Summary: A local data warehouse utility for managing and migrating data across DuckDB, Postgresql, SQLite, and CSV.
Home-page: https://github.com/thelaycon/mamaduck
License: MIT
Keywords: data warehouse,ETL,DuckDB,SQLite,CSV,Postgresql
Author: balogun
Author-email: tobitobitobiwhy@gmail.com
Requires-Python: >=3.10,<4.0
Classifier: Development Status :: 3 - Alpha
Classifier: Intended Audience :: Developers
Classifier: License :: OSI Approved :: MIT License
Classifier: Operating System :: OS Independent
Classifier: Programming Language :: Python :: 3
Classifier: Programming Language :: Python :: 3.10
Classifier: Programming Language :: Python :: 3.11
Classifier: Programming Language :: Python :: 3.12
Classifier: Programming Language :: Python :: 3.13
Classifier: Topic :: Database
Classifier: Topic :: Software Development :: Libraries
Requires-Dist: colorama (>=0.4.6,<0.5.0)
Requires-Dist: duckdb (>=1.1.3,<2.0.0)
Requires-Dist: pytest (>=8.3.4,<9.0.0)
Requires-Dist: sqlite-utils (>=3.35.1,<4.0.0)
Project-URL: Repository, https://github.com/thelaycon/mamaduck
